retsu/__init__.py
retsu/asyncio/__init__.py
retsu/asyncio/celery.py
retsu/asyncio/core.py
retsu/asyncio/queues.py
retsu/asyncio/results.py
retsu/celery.py
retsu/core.py
retsu/plugins/__init__.py
retsu/plugins/django.py
retsu/py.typed
retsu/queues.py
retsu/results.py
retsu-0.3.0.dist-info/LICENSE
retsu-0.3.0.dist-info/METADATA
retsu-0.3.0.dist-info/WHEEL
retsu-0.3.0.dist-info/RECORD
