Metadata-Version: 2.1
Name: retsu
Version: 0.3.0
Summary: Retsu aims to wrap-up Celery in way to facilitate to create parallel and serial tasks
License: BSD 3 Clause
Author: Ivan Ogasawara
Author-email: ivan.ogasawara@gmail.com
Requires-Python: >=3.8.1,<4
Classifier: License :: Other/Proprietary License
Classifier: Programming Language :: Python :: 3
Classifier: Programming Language :: Python :: 3.9
Classifier: Programming Language :: Python :: 3.10
Classifier: Programming Language :: Python :: 3.11
Classifier: Programming Language :: Python :: 3.12
Provides-Extra: django
Requires-Dist: asyncio (>=3.4.3)
Requires-Dist: atpublic (>=4.0)
Requires-Dist: celery (>=5)
Requires-Dist: django (>=3) ; extra == "django"
Requires-Dist: redis (>=5)
Requires-Dist: typing-extensions (>=4.12.0)
